ppxf/CHANGELOG.rst
ppxf/LICENSE.txt
ppxf/README.rst
ppxf/__init__.py
ppxf/ppxf.py
ppxf/ppxf_util.py
ppxf/sps_util.py
ppxf/examples/FILTER.RES.info.txt
ppxf/examples/FILTER.RES.txt
ppxf/examples/__init__.py
ppxf/examples/ppxf_example_gas_sdss_tied.py
ppxf/examples/ppxf_example_high_redshift.py
ppxf/examples/ppxf_example_integral_field.py
ppxf/examples/ppxf_example_integral_field_high_redshift.py
ppxf/examples/ppxf_example_kinematics_sauron.py
ppxf/examples/ppxf_example_kinematics_sdss.py
ppxf/examples/ppxf_example_legac_photometry.py
ppxf/examples/ppxf_example_montecarlo_simulation.py
ppxf/examples/ppxf_example_population_bootstrap.py
ppxf/examples/ppxf_example_population_gas_sdss.py
ppxf/examples/ppxf_example_population_photometry.py
ppxf/examples/ppxf_example_sky_and_symmetric_losvd.py
ppxf/examples/ppxf_example_two_components.py
ppxf/examples/ppxf_python_reference_output.txt
ppxf/spectra/NGC3073_SDSS_DR18.fits
ppxf/spectra/NGC3522_SDSS_DR18.fits
ppxf/spectra/NGC4550_SAURON.fits
ppxf/spectra/legac_M19_56670_v3.0.fits
ppxf/sps_models/spectra_sun_vega.npz
ppxf-9.4.5.dist-info/METADATA
ppxf-9.4.5.dist-info/WHEEL
ppxf-9.4.5.dist-info/top_level.txt
ppxf-9.4.5.dist-info/zip-safe
ppxf-9.4.5.dist-info/RECORD
