Metadata-Version: 2.4
Name: ppxf
Version: 9.4.5
Summary: pPXF: Full Spectrum and SED Fitting of Galactic and Stellar Spectra
Home-page: https://pypi.org/project/ppxf/
Author: Michele Cappellari
Author-email: michele.cappellari@physics.ox.ac.uk
License: Other/Proprietary License
Classifier: Development Status :: 5 - Production/Stable
Classifier: Intended Audience :: Developers
Classifier: Intended Audience :: Science/Research
Classifier: Operating System :: OS Independent
Classifier: Programming Language :: Python :: 3
Requires-Dist: capfit
Requires-Dist: numpy
Requires-Dist: scipy
Requires-Dist: matplotlib
Requires-Dist: astropy
Dynamic: author
Dynamic: author-email
Dynamic: classifier
Dynamic: description
Dynamic: description-content-type
Dynamic: home-page
Dynamic: license
Dynamic: requires-dist
Dynamic: summary
